{
  "$schema": "https://ui.shadcn.com/schema/registry-item.json",
  "name": "organization-switcher",
  "title": "Organization Switcher",
  "description": "A Better Auth organization switcher backed by the central Krakstack Auth client, with organization creation, editing, active organization switching, and organization API keys.",
  "dependencies": [
    "@better-auth/api-key",
    "@tanstack/react-table",
    "better-auth",
    "lucide-react",
    "react"
  ],
  "registryDependencies": [
    "badge",
    "button",
    "@krak/data-table",
    "dialog",
    "dropdown-menu",
    "form",
    "separator"
  ],
  "files": [
    {
      "path": "src/components/organization-switcher.tsx",
      "content": "import type { ApiKey } from \"@better-auth/api-key/client\";\nimport { type ColumnDef } from \"@tanstack/react-table\";\nimport { Building2, KeyRound, PencilIcon, Trash2 } from \"lucide-react\";\nimport {\n  type ComponentProps,\n  type ReactNode,\n  useEffect,\n  useEffectEvent,\n  useState,\n} from \"react\";\n\nimport {\n  createDataTableActionsColumn,\n  DataTable,\n} from \"@/components/data-table\";\nimport { useAppForm } from \"@/components/form\";\nimport { Badge } from \"@/components/ui/badge\";\nimport { Button } from \"@/components/ui/button\";\nimport {\n  Dialog,\n  DialogContent,\n  DialogDescription,\n  DialogHeader,\n  DialogTitle,\n} from \"@/components/ui/dialog\";\nimport {\n  DropdownMenu,\n  DropdownMenuContent,\n  DropdownMenuGroup,\n  DropdownMenuItem,\n  DropdownMenuLabel,\n  DropdownMenuSeparator,\n  DropdownMenuTrigger,\n} from \"@/components/ui/dropdown-menu\";\nimport { Separator } from \"@/components/ui/separator\";\nimport { m } from \"@/paraglide/messages\";\nimport { centralAuthClient } from \"@/services/auth/client/central\";\n\ntype OrganizationSwitcherProps = {\n  side?: ComponentProps<typeof DropdownMenuContent>[\"side\"];\n  renderUnauthenticated?: () => ReactNode;\n};\n\ntype OrganizationSummary = {\n  id: string;\n  name: string;\n  slug: string;\n};\n\ntype OrganizationDialog = \"create\" | \"manage\" | \"apiKeys\";\ntype ApiKeySummary = Omit<ApiKey, \"key\">;\n\nconst slugify = (value: string) =>\n  value\n    .trim()\n    .toLowerCase()\n    .replace(/[^a-z0-9]+/g, \"-\")\n    .replace(/^-+|-+$/g, \"\");\n\nexport function OrganizationSwitcher({\n  side = \"bottom\",\n  renderUnauthenticated,\n}: OrganizationSwitcherProps) {\n  const session = centralAuthClient.useSession();\n  const organizations = centralAuthClient.useListOrganizations();\n  const activeOrganization = centralAuthClient.useActiveOrganization();\n  const [dialog, setDialog] = useState<OrganizationDialog | null>(null);\n\n  if (!session.data) {\n    return <>{renderUnauthenticated?.()}</>;\n  }\n\n  const active = activeOrganization.data;\n  const activeName = active?.name;\n  const selectableOrganizations =\n    organizations.data?.filter(\n      (organization) => organization.id !== active?.id,\n    ) ?? [];\n\n  const refresh = async () => {\n    await organizations.refetch();\n    await activeOrganization.refetch();\n  };\n\n  return (\n    <>\n      <DropdownMenu>\n        <DropdownMenuTrigger\n          render={\n            <Button variant=\"outline\" className=\"max-w-48 justify-start\">\n              <Building2 data-icon=\"inline-start\" />\n              <span className=\"truncate\">\n                {activeName ?? m.organization_switcher_label()}\n              </span>\n            </Button>\n          }\n        />\n        <DropdownMenuContent\n          className=\"min-w-64 rounded-lg\"\n          side={side}\n          align=\"end\"\n          sideOffset={4}\n        >\n          <DropdownMenuGroup>\n            <DropdownMenuLabel className=\"p-0 font-normal\">\n              <div className=\"flex items-center gap-2 px-1 py-1.5 text-left text-sm\">\n                <Building2 className=\"size-4.5\" />\n                <div className=\"grid flex-1 text-left text-sm leading-tight\">\n                  {active ? (\n                    <>\n                      <span className=\"text-foreground truncate font-medium\">\n                        {active.name}\n                      </span>\n                      <span className=\"text-muted-foreground truncate text-xs\">\n                        {active.slug}\n                      </span>\n                    </>\n                  ) : (\n                    <span className=\"text-foreground truncate font-medium\">\n                      {m.organization_switcher_label()}\n                    </span>\n                  )}\n                </div>\n              </div>\n            </DropdownMenuLabel>\n            <DropdownMenuSeparator />\n            {organizations.isPending ? (\n              <DropdownMenuItem disabled>\n                {m.organization_loading()}\n              </DropdownMenuItem>\n            ) : null}\n            {organizations.error ? (\n              <DropdownMenuItem disabled>\n                {organizations.error.message}\n              </DropdownMenuItem>\n            ) : null}\n            {selectableOrganizations.length ? (\n              selectableOrganizations.map((organization) => (\n                <DropdownMenuItem\n                  key={organization.id}\n                  onClick={async () => {\n                    const result =\n                      await centralAuthClient.organization.setActive({\n                        organizationId: organization.id,\n                      });\n                    if (!result.error) await refresh();\n                  }}\n                >\n                  <Building2 />\n                  <span className=\"truncate\">{organization.name}</span>\n                </DropdownMenuItem>\n              ))\n            ) : !organizations.isPending ? (\n              <DropdownMenuItem disabled>\n                {active\n                  ? m.organization_switcher_no_other_organizations()\n                  : m.organization_switcher_empty()}\n              </DropdownMenuItem>\n            ) : null}\n            <DropdownMenuSeparator />\n            <DropdownMenuItem onClick={() => setDialog(\"create\")}>\n              <Building2 />\n              {m.organization_create_title()}\n            </DropdownMenuItem>\n            {activeOrganization.data ? (\n              <>\n                <DropdownMenuSeparator />\n                <DropdownMenuItem onClick={() => setDialog(\"manage\")}>\n                  <PencilIcon />\n                  {m.organization_switcher_manage()}\n                </DropdownMenuItem>\n                <DropdownMenuItem onClick={() => setDialog(\"apiKeys\")}>\n                  <KeyRound />\n                  {m.user_button_api_keys()}\n                </DropdownMenuItem>\n              </>\n            ) : null}\n          </DropdownMenuGroup>\n        </DropdownMenuContent>\n      </DropdownMenu>\n      <Dialog\n        open={dialog === \"create\"}\n        onOpenChange={(open) => {\n          setDialog((current) =>\n            open ? \"create\" : current === \"create\" ? null : current,\n          );\n        }}\n      >\n        <DialogContent className=\"max-h-[85vh] overflow-y-auto sm:max-w-3xl\">\n          <DialogHeader>\n            <DialogTitle className=\"text-2xl\">\n              {m.organization_create_title()}\n            </DialogTitle>\n            <DialogDescription>\n              {m.organization_create_description()}\n            </DialogDescription>\n          </DialogHeader>\n          <Separator />\n          <CreateOrganizationSection\n            onCreated={async () => {\n              await refresh();\n              setDialog(null);\n            }}\n          />\n        </DialogContent>\n      </Dialog>\n      <Dialog\n        open={dialog === \"manage\"}\n        onOpenChange={(open) => {\n          setDialog((current) =>\n            open ? \"manage\" : current === \"manage\" ? null : current,\n          );\n        }}\n      >\n        <DialogContent className=\"max-h-[85vh] overflow-y-auto sm:max-w-3xl\">\n          <DialogHeader>\n            <DialogTitle className=\"text-2xl\">\n              {m.organization_switcher_manage()}\n            </DialogTitle>\n            <DialogDescription>{m.organization_edit_description()}</DialogDescription>\n          </DialogHeader>\n          <Separator />\n          {activeOrganization.data ? (\n            <EditOrganizationSection\n              organization={activeOrganization.data}\n              onUpdated={refresh}\n            />\n          ) : null}\n        </DialogContent>\n      </Dialog>\n      <Dialog\n        open={dialog === \"apiKeys\"}\n        onOpenChange={(open) => {\n          setDialog((current) =>\n            open ? \"apiKeys\" : current === \"apiKeys\" ? null : current,\n          );\n        }}\n      >\n        <DialogContent className=\"max-h-[85vh] overflow-y-auto sm:max-w-3xl\">\n          <DialogHeader>\n            <DialogTitle className=\"text-2xl\">\n              {m.user_api_keys_title()}\n            </DialogTitle>\n            <DialogDescription>{activeOrganization.data?.name}</DialogDescription>\n          </DialogHeader>\n          <Separator />\n          {activeOrganization.data ? (\n            <OrganizationApiKeyManager organization={activeOrganization.data} />\n          ) : null}\n        </DialogContent>\n      </Dialog>\n    </>\n  );\n}\n\nfunction EditOrganizationSection({\n  organization,\n  onUpdated,\n}: {\n  organization: OrganizationSummary;\n  onUpdated: () => Promise<void>;\n}) {\n  const form = useAppForm({\n    defaultValues: {\n      name: organization.name,\n      slug: organization.slug,\n    },\n    onSubmit: async ({ value, formApi }) => {\n      formApi.setErrorMap({ onSubmit: undefined });\n      const name = value.name.trim();\n      const slug = value.slug.trim().toLowerCase();\n\n      const result = await centralAuthClient.organization.update({\n        organizationId: organization.id,\n        data: { name, slug },\n      });\n\n      if (result.error) {\n        formApi.setErrorMap({\n          onSubmit: {\n            form: result.error.message ?? m.organization_update_error(),\n            fields: {},\n          },\n        });\n        return;\n      }\n\n      await onUpdated();\n    },\n  });\n\n  return (\n    <section className=\"flex flex-col gap-4\">\n      <form.AppForm>\n        <form\n          className=\"flex max-w-xl flex-col gap-4\"\n          onSubmit={(event) => {\n            event.preventDefault();\n            event.stopPropagation();\n            form.handleSubmit();\n          }}\n        >\n          <form.AppField name=\"name\">\n            {(field) => (\n              <field.TextField label={m.organization_name()} required />\n            )}\n          </form.AppField>\n          <form.AppField name=\"slug\">\n            {(field) => (\n              <field.TextField label={m.organization_slug()} required />\n            )}\n          </form.AppField>\n          <form.FormError />\n          <form.SubmitButton />\n        </form>\n      </form.AppForm>\n    </section>\n  );\n}\n\nfunction CreateOrganizationSection({\n  onCreated,\n}: {\n  onCreated: () => Promise<void>;\n}) {\n  const form = useAppForm({\n    defaultValues: { name: \"\", slug: \"\" },\n    onSubmit: async ({ value, formApi }) => {\n      formApi.setErrorMap({ onSubmit: undefined });\n      const name = value.name.trim();\n      const slug = (value.slug.trim() || slugify(name)).toLowerCase();\n\n      const result = await centralAuthClient.organization.create({\n        name,\n        slug,\n      });\n\n      if (result.error) {\n        formApi.setErrorMap({\n          onSubmit: {\n            form: result.error.message ?? m.organization_create_error(),\n            fields: {},\n          },\n        });\n        return;\n      }\n\n      form.reset();\n      await onCreated();\n    },\n  });\n\n  return (\n    <section className=\"flex flex-col gap-4\">\n      <form.AppForm>\n        <form\n          className=\"flex max-w-xl flex-col gap-4\"\n          onSubmit={(event) => {\n            event.preventDefault();\n            event.stopPropagation();\n            form.handleSubmit();\n          }}\n        >\n          <form.AppField name=\"name\">\n            {(field) => (\n              <field.TextField label={m.organization_name()} required />\n            )}\n          </form.AppField>\n          <form.AppField name=\"slug\">\n            {(field) => (\n              <field.TextField\n                label={m.organization_slug()}\n                description={m.organization_slug_description()}\n              />\n            )}\n          </form.AppField>\n          <form.FormError />\n          <form.SubmitButton />\n        </form>\n      </form.AppForm>\n    </section>\n  );\n}\n\nfunction OrganizationApiKeyManager({\n  organization,\n}: {\n  organization: OrganizationSummary;\n}) {\n  const [keys, setKeys] = useState<ApiKeySummary[]>([]);\n  const [createdKey, setCreatedKey] = useState<string | null>(null);\n  const [error, setError] = useState<string | null>(null);\n  const [loading, setLoading] = useState(true);\n\n  const loadKeys = useEffectEvent(async () => {\n    setLoading(true);\n    setError(null);\n    const result = await centralAuthClient.apiKey.list({\n      query: { configId: \"organization\", organizationId: organization.id },\n    });\n\n    if (result.error) {\n      setError(result.error.message ?? m.user_api_keys_load_error());\n      setLoading(false);\n      return;\n    }\n\n    setKeys(result.data?.apiKeys ?? []);\n    setLoading(false);\n  });\n\n  useEffect(() => {\n    void loadKeys();\n  }, [organization.id]);\n\n  const createForm = useAppForm({\n    defaultValues: { name: \"\" },\n    onSubmit: async ({ value, formApi }) => {\n      formApi.setErrorMap({ onSubmit: undefined });\n      setCreatedKey(null);\n      const result = await centralAuthClient.apiKey.create({\n        configId: \"organization\",\n        organizationId: organization.id,\n        name: value.name.trim(),\n      });\n\n      if (result.error || !result.data) {\n        formApi.setErrorMap({\n          onSubmit: {\n            form: result.error?.message ?? m.user_api_key_create_error(),\n            fields: {},\n          },\n        });\n        return;\n      }\n\n      setCreatedKey(result.data.key);\n      createForm.reset();\n      await loadKeys();\n    },\n  });\n\n  const deleteKey = async (key: ApiKeySummary) => {\n    const result = await centralAuthClient.apiKey.delete({\n      configId: \"organization\",\n      keyId: key.id,\n    });\n\n    if (result.error) {\n      setError(result.error.message ?? m.user_api_key_delete_error());\n      return;\n    }\n\n    await loadKeys();\n  };\n\n  return (\n    <div className=\"flex flex-col gap-5\">\n      <createForm.AppForm>\n        <form\n          className=\"flex max-w-xl flex-col gap-4\"\n          onSubmit={(event) => {\n            event.preventDefault();\n            event.stopPropagation();\n            createForm.handleSubmit();\n          }}\n        >\n          <createForm.AppField name=\"name\">\n            {(field) => (\n              <field.TextField label={m.user_api_key_name()} required />\n            )}\n          </createForm.AppField>\n          <createForm.FormError />\n          <createForm.SubmitButton />\n        </form>\n      </createForm.AppForm>\n      {createdKey ? (\n        <div className=\"flex flex-col gap-2 rounded-lg border p-4\">\n          <div className=\"flex items-center gap-2 font-medium\">\n            <KeyRound />\n            {m.user_api_key_created_title()}\n          </div>\n          <p className=\"text-muted-foreground text-sm\">\n            {m.user_api_key_created_description()}\n          </p>\n          <code className=\"bg-muted overflow-x-auto rounded-md p-3 text-sm\">\n            {createdKey}\n          </code>\n        </div>\n      ) : null}\n      {error ? <p className=\"text-destructive text-sm\">{error}</p> : null}\n      {loading ? (\n        <p className=\"text-muted-foreground text-sm\">{m.user_loading()}</p>\n      ) : null}\n      <Separator />\n      <DataTable\n        from=\"/\"\n        columns={apiKeyColumns({ onDelete: deleteKey })}\n        data={keys}\n        exportFileName={`${organization.slug}-api-keys.csv`}\n        features={{ gallery: false }}\n      />\n    </div>\n  );\n}\n\nconst apiKeyColumns = ({\n  onDelete,\n}: {\n  onDelete: (key: ApiKeySummary) => void;\n}): ColumnDef<ApiKeySummary>[] => [\n  {\n    accessorKey: \"name\",\n    header: m.user_api_key_name(),\n    cell: ({ row }) => (\n      <div className=\"min-w-0\">\n        <p className=\"truncate font-medium\">{row.original.name}</p>\n        <p className=\"text-muted-foreground text-sm\">\n          {row.original.start\n            ? m.user_api_key_starts_with({ start: row.original.start })\n            : m.user_api_key_hidden()}\n        </p>\n      </div>\n    ),\n  },\n  {\n    accessorKey: \"enabled\",\n    header: m.user_api_key_status(),\n    cell: ({ row }) => (\n      <Badge variant={row.original.enabled ? \"default\" : \"secondary\"}>\n        {row.original.enabled\n          ? m.user_api_key_enabled()\n          : m.user_api_key_disabled()}\n      </Badge>\n    ),\n  },\n  createDataTableActionsColumn<ApiKeySummary>([\n    {\n      name: m.user_delete(),\n      icon: <Trash2 />,\n      variant: \"destructive\",\n      onClick: onDelete,\n    },\n  ]),\n];\n",
      "type": "registry:component",
      "target": "components/organization-switcher.tsx"
    },
    {
      "path": "src/services/auth/client/central.ts",
      "content": "import { apiKeyClient } from \"@better-auth/api-key/client\";\nimport { createAuthClient } from \"better-auth/react\";\nimport {\n  organizationClient,\n  twoFactorClient,\n} from \"better-auth/client/plugins\";\n\nexport const centralAuthClient = createAuthClient({\n  baseURL: import.meta.env.VITE_KRAKSTACK_AUTH_URL,\n  fetchOptions: {\n    credentials: \"include\",\n  },\n  plugins: [\n    twoFactorClient({\n      onTwoFactorRedirect: () => {\n        window.location.href = `${import.meta.env.VITE_KRAKSTACK_AUTH_URL}/2fa`;\n      },\n    }),\n    organizationClient(),\n    apiKeyClient(),\n  ],\n});\n",
      "type": "registry:file",
      "target": "services/auth/client/central.ts"
    },
    {
      "path": "src/messages/components/organization-switcher/en.json",
      "content": "{\n  \"organizations_title\": \"Organizations\",\n  \"organizations_description\": \"Create, edit, and switch between organizations you belong to.\",\n  \"organization_create_title\": \"Create organization\",\n  \"organization_create_description\": \"Create a workspace for team-based access.\",\n  \"organization_edit_title\": \"Edit organization\",\n  \"organization_edit_description\": \"Update the active organization's name and slug.\",\n  \"organization_name\": \"Organization name\",\n  \"organization_slug\": \"Organization slug\",\n  \"organization_slug_description\": \"Leave blank to generate one from the name.\",\n  \"organization_create_error\": \"Could not create the organization.\",\n  \"organization_update_error\": \"Could not update the organization.\",\n  \"organization_switcher_empty\": \"You do not belong to any organizations yet.\",\n  \"organization_switcher_no_other_organizations\": \"No other organizations.\",\n  \"organization_switcher_label\": \"Organization\",\n  \"organization_switcher_manage\": \"Manage organization\",\n  \"organization_loading\": \"Loading...\",\n  \"user_button_api_keys\": \"API keys\",\n  \"user_api_keys_title\": \"API keys\",\n  \"user_api_keys_load_error\": \"Could not load API keys.\",\n  \"user_api_key_name\": \"Key name\",\n  \"user_api_key_status\": \"Status\",\n  \"user_api_key_create_error\": \"Could not create the API key.\",\n  \"user_api_key_delete_error\": \"Could not delete the API key.\",\n  \"user_api_key_created_title\": \"API key created\",\n  \"user_api_key_created_description\": \"Copy this key now. You will not be able to see it again.\",\n  \"user_api_key_enabled\": \"Enabled\",\n  \"user_api_key_disabled\": \"Disabled\",\n  \"user_api_key_hidden\": \"Secret hidden\",\n  \"user_api_key_starts_with\": \"Starts with {start}\",\n  \"user_loading\": \"Loading...\",\n  \"user_delete\": \"Delete\"\n}\n",
      "type": "registry:file",
      "target": "./messages/components/organization-switcher/en.json"
    },
    {
      "path": "src/messages/components/organization-switcher/fr.json",
      "content": "{\n  \"organizations_title\": \"Organisations\",\n  \"organizations_description\": \"Créez, modifiez et basculez entre les organisations auxquelles vous appartenez.\",\n  \"organization_create_title\": \"Créer une organisation\",\n  \"organization_create_description\": \"Créez un espace de travail pour l'accès en équipe.\",\n  \"organization_edit_title\": \"Modifier l'organisation\",\n  \"organization_edit_description\": \"Mettez à jour le nom et le slug de l'organisation active.\",\n  \"organization_name\": \"Nom de l'organisation\",\n  \"organization_slug\": \"Slug de l'organisation\",\n  \"organization_slug_description\": \"Laissez vide pour en générer un à partir du nom.\",\n  \"organization_create_error\": \"Impossible de créer l'organisation.\",\n  \"organization_update_error\": \"Impossible de mettre à jour l'organisation.\",\n  \"organization_switcher_empty\": \"Vous n'appartenez encore à aucune organisation.\",\n  \"organization_switcher_no_other_organizations\": \"Aucune autre organisation.\",\n  \"organization_switcher_label\": \"Organisation\",\n  \"organization_switcher_manage\": \"Gérer l'organisation\",\n  \"organization_loading\": \"Chargement...\",\n  \"user_button_api_keys\": \"Clés API\",\n  \"user_api_keys_title\": \"Clés API\",\n  \"user_api_keys_load_error\": \"Impossible de charger les clés API.\",\n  \"user_api_key_name\": \"Nom de la clé\",\n  \"user_api_key_status\": \"Statut\",\n  \"user_api_key_create_error\": \"Impossible de créer la clé API.\",\n  \"user_api_key_delete_error\": \"Impossible de supprimer la clé API.\",\n  \"user_api_key_created_title\": \"Clé API créée\",\n  \"user_api_key_created_description\": \"Copiez cette clé maintenant. Vous ne pourrez plus la voir.\",\n  \"user_api_key_enabled\": \"Activée\",\n  \"user_api_key_disabled\": \"Désactivée\",\n  \"user_api_key_hidden\": \"Secret masqué\",\n  \"user_api_key_starts_with\": \"Commence par {start}\",\n  \"user_loading\": \"Chargement...\",\n  \"user_delete\": \"Supprimer\"\n}\n",
      "type": "registry:file",
      "target": "./messages/components/organization-switcher/fr.json"
    }
  ],
  "docs": "## Overview\n\n`organization-switcher` provides an organization-aware dropdown for apps using Krakstack Auth as the central identity provider. It uses `centralAuthClient` so the active organization, memberships, and organization API keys stay scoped to the central auth service rather than the app-local session.\n\n## Features\n\n- Central Krakstack Auth organization list and active organization state\n- Create organizations and auto-generate slugs\n- Switch between organizations\n- Edit the active organization's name and slug\n- Manage organization-scoped API keys\n- Configurable unauthenticated render slot\n- Localized menu and form labels\n\n## Usage\n\n```tsx\nimport { OrganizationSwitcher } from \"@/components/organization-switcher\";\n\n<OrganizationSwitcher side=\"bottom\" />\n```\n\nSet `VITE_KRAKSTACK_AUTH_URL` to your central auth origin, for example `http://localhost:3001`. The central auth server must have Better Auth's organization and API-key plugins enabled.",
  "type": "registry:block"
}